graphene_django_flufy/__init__.py
graphene_django_flufy/base_types.py
graphene_django_flufy/converter.py
graphene_django_flufy/directives/__init__.py
graphene_django_flufy/directives/base.py
graphene_django_flufy/directives/date.py
graphene_django_flufy/directives/list.py
graphene_django_flufy/directives/numbers.py
graphene_django_flufy/directives/string.py
graphene_django_flufy/fields.py
graphene_django_flufy/filters/__init__.py
graphene_django_flufy/filters/filter.py
graphene_django_flufy/filters/lookups.py
graphene_django_flufy/middleware.py
graphene_django_flufy/mutation.py
graphene_django_flufy/paginations/__init__.py
graphene_django_flufy/paginations/fields.py
graphene_django_flufy/paginations/pagination.py
graphene_django_flufy/paginations/utils.py
graphene_django_flufy/registry.py
graphene_django_flufy/settings.py
graphene_django_flufy/types.py
graphene_django_flufy/utils.py
graphene_django_flufy/views.py
graphene_django_flufy-0.1.6.dist-info/LICENSE
graphene_django_flufy-0.1.6.dist-info/WHEEL
graphene_django_flufy-0.1.6.dist-info/METADATA
graphene_django_flufy-0.1.6.dist-info/RECORD
