Metadata-Version: 2.1
Name: graphene-django-flufy
Version: 0.1.6
Summary: This library add some extra funcionalities to graphene-django to facilitate the graphql use without Relay, allow paginations and filtering integration and add some extra directives
Home-page: https://github.com/profmcdan/graphene-django-flufy
License: MIT
Keywords: api,graphql,protocol,graphene,django
Author: Daniel Ale
Author-email: danielale9291@gmail.com
Requires-Python: >=3.9,<4.0.0
Classifier: Intended Audience :: Developers
Classifier: License :: OSI Approved :: MIT License
Classifier: Programming Language :: Python :: 3
Classifier: Programming Language :: Python :: 3.9
Classifier: Programming Language :: Python :: 3.10
Classifier: Programming Language :: Python :: 3.11
Classifier: Programming Language :: Python :: 3.10
Classifier: Programming Language :: Python :: 3.7
Classifier: Programming Language :: Python :: 3.8
Classifier: Programming Language :: Python :: 3.9
Classifier: Programming Language :: Python :: Implementation :: PyPy
Classifier: Topic :: Software Development :: Libraries
Requires-Dist: django-filter (>=22.1,<23.0)
Requires-Dist: djangorestframework (>=3.14.0,<4.0.0)
Requires-Dist: graphene-django (>=3.0.0,<4.0.0)
Requires-Dist: graphql-core (>=3.2.3,<4.0.0)
Requires-Dist: python-dateutil (>=2.8.2,<3.0.0)
Requires-Dist: rx (>=3.2.0,<4.0.0)
Requires-Dist: toml (>=0.10.2,<0.11.0)
Project-URL: Documentation, https://github.com/profmcdan/graphene-django-flufy
Project-URL: Repository, https://github.com/profmcdan/graphene-django-flufy
